gpodder_export/__init__.py
gpodder_export/main.py
gpodder_exporter/__init__.py
gpodder_exporter/main.py
gpodder_exporter-0.1.0.dist-info/METADATA
gpodder_exporter-0.1.0.dist-info/WHEEL
gpodder_exporter-0.1.0.dist-info/entry_points.txt
gpodder_exporter-0.1.0.dist-info/top_level.txt
gpodder_exporter-0.1.0.dist-info/RECORD
