Metadata-Version: 2.1
Name: gpodder-exporter
Version: 0.1.0
Summary: A CLI tool to export gPodder podcast titles and RSS URLs to a CSV file
Home-page: https://github.com/gusanmaz/gpodder-export
Author: Guvenc USANMAZ
Author-email: gusanmaz@gmail.com
Classifier: Development Status :: 3 - Alpha
Classifier: Intended Audience :: End Users/Desktop
Classifier: License :: OSI Approved :: MIT License
Classifier: Programming Language :: Python :: 3
Classifier: Programming Language :: Python :: 3.6
Classifier: Programming Language :: Python :: 3.7
Classifier: Programming Language :: Python :: 3.8
Classifier: Programming Language :: Python :: 3.9
Classifier: Programming Language :: Python :: 3.10
Classifier: Programming Language :: Python :: 3.11
